django_counter_field/__init__.py
django_counter_field/_version.py
django_counter_field/counter.py
django_counter_field/fields.py
django_counter_field-2.0.0.dist-info/licenses/LICENSE
django_counter_field-2.0.0.dist-info/METADATA
django_counter_field-2.0.0.dist-info/WHEEL
django_counter_field-2.0.0.dist-info/top_level.txt
django_counter_field-2.0.0.dist-info/RECORD
