Metadata-Version: 2.4
Name: django-counter-field
Version: 2.0.0
Summary: Django counter field for tracking related model counts
Author-email: Robert Kajic <robert@kajic.com>
License-Expression: MIT
Project-URL: Homepage, https://github.com/kajic/django-counter-field
Project-URL: Repository, https://github.com/kajic/django-counter-field
Classifier: Environment :: Web Environment
Classifier: Framework :: Django
Classifier: Framework :: Django :: 5.0
Classifier: Framework :: Django :: 5.1
Classifier: Framework :: Django :: 6.0
Classifier: Intended Audience :: Developers
Classifier: Operating System :: OS Independent
Classifier: Programming Language :: Python :: 3
Classifier: Programming Language :: Python :: 3.14
Requires-Python: >=3.14
License-File: LICENSE
Requires-Dist: django<7.0,>=5.0
Requires-Dist: django-model-changes>=1.0.3
Dynamic: license-file
